kvadrat.py
kvadrat_kutarish-0.2.0.dist-info/licenses/LICENSE
kvadrat_kutarish-0.2.0.dist-info/METADATA
kvadrat_kutarish-0.2.0.dist-info/WHEEL
kvadrat_kutarish-0.2.0.dist-info/top_level.txt
kvadrat_kutarish-0.2.0.dist-info/RECORD
