Metadata-Version: 2.4
Name: kvadrat_kutarish
Version: 0.2.0
Summary: Oddiy kvadrat hisoblovchi funksiya
Author-email: ibratjon <xoshimovibratjon3@gmail.com>
Requires-Python: >=3.8
License-File: LICENSE
Dynamic: license-file
